plumbingbird/etl/extractors/__init__.py
plumbingbird/etl/extractors/api_fetcher.py
plumbingbird/etl/loaders/__init__.py
plumbingbird/etl/loaders/postgres_loaders.py
plumbingbird/etl/transformers/__init__.py
plumbingbird/etl/transformers/csv_streamer.py
plumbingbird/orchestration/__init__.py
plumbingbird/orchestration/aws/__init__.py
plumbingbird/orchestration/aws/infra.py
plumbingbird/orchestration/aws/job.py
plumbingbird/orchestration/aws/utilities.py
plumbingbird/orchestration/gcp/__init__.py
plumbingbird/tests/__init__.py
plumbingbird/tests/demo/__init__.py
plumbingbird/tests/demo/dummy_api_fetcher.py
plumbingbird/tests/demo/pypi-token.txt
plumbingbird/tests/integration_tests/__init__.py
plumbingbird/tests/integration_tests/test_buffer.py
plumbingbird/tests/integration_tests/test_fetcher.py
plumbingbird/utilities/__init__.py
plumbingbird/utilities/environment.py
plumbingbird/utilities/etl_primitives.py
plumbingbird/utilities/orchestration_primitives.py
plumbingbird/utilities/streamer.py
plumbingbird-0.1.0.dist-info/LICENSE
plumbingbird-0.1.0.dist-info/METADATA
plumbingbird-0.1.0.dist-info/WHEEL
plumbingbird-0.1.0.dist-info/RECORD
