Metadata-Version: 2.1
Name: plumbingbird
Version: 0.1.0
Summary: Handy tools for common data engineering needs.
License: GNU GPLv3
Author: Rebecca Lovering
Author-email: lovering810@gmail.com
Requires-Python: >=3.12,<4.0
Classifier: License :: Other/Proprietary License
Classifier: Programming Language :: Python :: 3
Classifier: Programming Language :: Python :: 3.12
Requires-Dist: boto3 (>=1.7.84,<2.0.0)
Requires-Dist: psycopg2
Requires-Dist: pytest
Requires-Dist: python-dotenv
Requires-Dist: pyyaml
Requires-Dist: requests
Requires-Dist: smart_open
